[
  {
    "inter": {
      "time": "2012-01-12T03:04:23.65524201082Z",
      "lat": -33.36051243,
      "fixFrac": 32.1655242010828,
      "lng": 147.93241172,
      "alt": 306.64
    },
    "cross": {
      "inZone": [
        false,
        true
      ],
      "crossingPair": [
        {
          "time": "2012-01-12T03:04:22Z",
          "lat": -33.360333,
          "fix": 32,
          "lng": 147.932467,
          "alt": 303
        },
        {
          "time": "2012-01-12T03:04:32Z",
          "lat": -33.361417,
          "fix": 33,
          "lng": 147.932133,
          "alt": 325
        }
      ]
    }
  },
  {
    "inter": {
      "time": "2012-01-12T03:36:33.23271273025Z",
      "lat": -33.22582111,
      "fixFrac": 224.92327127302562,
      "lng": 147.9290286,
      "alt": 1574.46
    },
    "cross": {
      "inZone": [
        true,
        false
      ],
      "crossingPair": [
        {
          "time": "2012-01-12T03:36:24Z",
          "lat": -33.227483,
          "fix": 224,
          "lng": 147.928567,
          "alt": 1568
        },
        {
          "time": "2012-01-12T03:36:34Z",
          "lat": -33.225683,
          "fix": 225,
          "lng": 147.929067,
          "alt": 1575
        }
      ]
    }
  },
  null,
  null
]
