[
  {
    "inter": {
      "time": "2012-01-12T02:25:56.78811104568Z",
      "lat": -33.36222234,
      "fixFrac": 51.47881110456824,
      "lng": 147.93171001,
      "alt": 615.22
    },
    "cross": {
      "inZone": [
        false,
        true
      ],
      "crossingPair": [
        {
          "time": "2012-01-12T02:25:52Z",
          "lat": -33.3631,
          "fix": 51,
          "lng": 147.932117,
          "alt": 609
        },
        {
          "time": "2012-01-12T02:26:02Z",
          "lat": -33.361267,
          "fix": 52,
          "lng": 147.931267,
          "alt": 622
        }
      ]
    }
  },
  {
    "inter": {
      "time": "2012-01-12T03:15:57.53326580058Z",
      "lat": -33.22697635,
      "fixFrac": 350.5533265800589,
      "lng": 147.95341477,
      "alt": 1742.47
    },
    "cross": {
      "inZone": [
        true,
        false
      ],
      "crossingPair": [
        {
          "time": "2012-01-12T03:15:52Z",
          "lat": -33.228083,
          "fix": 350,
          "lng": 147.95335,
          "alt": 1748
        },
        {
          "time": "2012-01-12T03:16:02Z",
          "lat": -33.226083,
          "fix": 351,
          "lng": 147.953467,
          "alt": 1738
        }
      ]
    }
  },
  {
    "inter": {
      "time": "2012-01-12T05:39:29.063221910629Z",
      "lat": -32.23131491,
      "fixFrac": 1210.4514691011816,
      "lng": 147.79393849,
      "alt": 1866.65
    },
    "cross": {
      "inZone": [
        false,
        true
      ],
      "crossingPair": [
        {
          "time": "2012-01-12T05:39:25Z",
          "lat": -32.2313,
          "fix": 1210,
          "lng": 147.79445,
          "alt": 1868
        },
        {
          "time": "2012-01-12T05:39:34Z",
          "lat": -32.231333,
          "fix": 1211,
          "lng": 147.793317,
          "alt": 1865
        }
      ]
    }
  },
  {
    "inter": {
      "time": "2012-01-12T06:57:11.24085758019Z",
      "lat": -31.6931452,
      "fixFrac": 1675.7240857580193,
      "lng": 148.29611911,
      "alt": 354.21
    },
    "cross": {
      "inZone": [
        false,
        true
      ],
      "crossingPair": [
        {
          "time": "2012-01-12T06:57:04Z",
          "lat": -31.694883,
          "fix": 1675,
          "lng": 148.29455,
          "alt": 381
        },
        {
          "time": "2012-01-12T06:57:14Z",
          "lat": -31.692483,
          "fix": 1676,
          "lng": 148.296717,
          "alt": 344
        }
      ]
    }
  }
]
