[
  null,
  {
    "inter": {
      "time": "2012-01-12T03:24:24.028330280996Z",
      "lat": -33.22697428,
      "fixFrac": 1011.5141651404984,
      "lng": 147.94598725
    },
    "cross": {
      "inZone": [
        true,
        false
      ],
      "crossingPair": [
        {
          "time": "2012-01-12T03:24:23Z",
          "lat": -33.227,
          "fix": 1011,
          "lng": 147.945833
        },
        {
          "time": "2012-01-12T03:24:25Z",
          "lat": -33.22695,
          "fix": 1012,
          "lng": 147.946133
        }
      ]
    }
  },
  {
    "inter": {
      "time": "2012-01-12T05:45:56.748438599246Z",
      "lat": -32.23678759,
      "fixFrac": 5238.874219299624,
      "lng": 147.78174772
    },
    "cross": {
      "inZone": [
        false,
        true
      ],
      "crossingPair": [
        {
          "time": "2012-01-12T05:45:55Z",
          "lat": -32.237167,
          "fix": 5238,
          "lng": 147.78185
        },
        {
          "time": "2012-01-12T05:45:57Z",
          "lat": -32.236733,
          "fix": 5239,
          "lng": 147.781733
        }
      ]
    }
  },
  {
    "inter": {
      "time": "2012-01-12T07:20:11.517888883356Z",
      "lat": -31.69329548,
      "fixFrac": 8058.758944441679,
      "lng": 148.29631563
    },
    "cross": {
      "inZone": [
        false,
        true
      ],
      "crossingPair": [
        {
          "time": "2012-01-12T07:20:10Z",
          "lat": -31.6937,
          "fix": 8058,
          "lng": 148.29605
        },
        {
          "time": "2012-01-12T07:20:12Z",
          "lat": -31.693167,
          "fix": 8059,
          "lng": 148.2964
        }
      ]
    }
  }
]
