[
  null,
  {
    "inter": {
      "time": "2012-01-12T03:31:37.682624475968Z",
      "lat": -33.22930549,
      "fixFrac": 998.8413122379841,
      "lng": 147.96497603
    },
    "cross": {
      "inZone": [
        true,
        false
      ],
      "crossingPair": [
        {
          "time": "2012-01-12T03:31:36Z",
          "lat": -33.2296,
          "fix": 998,
          "lng": 147.96485
        },
        {
          "time": "2012-01-12T03:31:38Z",
          "lat": -33.22925,
          "fix": 999,
          "lng": 147.965
        }
      ]
    }
  },
  null,
  null
]
