[
  {
    "inter": {
      "time": "2012-01-12T02:01:12.86054082514Z",
      "lat": -33.36053947,
      "fixFrac": 33.6860540825148,
      "lng": 147.93165697
    },
    "cross": {
      "inZone": [
        false,
        true
      ],
      "crossingPair": [
        {
          "time": "2012-01-12T02:01:06Z",
          "lat": -33.359933,
          "fix": 33,
          "lng": 147.932
        },
        {
          "time": "2012-01-12T02:01:16Z",
          "lat": -33.360817,
          "fix": 34,
          "lng": 147.9315
        }
      ]
    }
  },
  {
    "inter": {
      "time": "2012-01-12T03:12:50.20878014475Z",
      "lat": -33.23272846,
      "fixFrac": 462.0208780144752,
      "lng": 147.98065197
    },
    "cross": {
      "inZone": [
        true,
        false
      ],
      "crossingPair": [
        {
          "time": "2012-01-12T03:12:50Z",
          "lat": -33.23275,
          "fix": 462,
          "lng": 147.980667
        },
        {
          "time": "2012-01-12T03:13:00Z",
          "lat": -33.231717,
          "fix": 463,
          "lng": 147.97995
        }
      ]
    }
  },
  null,
  null
]
