[
  null,
  {
    "inter": {
      "time": "2012-01-10T03:35:52.05112816643Z",
      "lat": -33.23228065,
      "fixFrac": 582.6102256332865,
      "lng": 147.98162926,
      "alt": 1764.73
    },
    "cross": {
      "inZone": [
        true,
        false
      ],
      "crossingPair": [
        {
          "time": "2012-01-10T03:35:49Z",
          "lat": -33.23285,
          "fix": 582,
          "lng": 147.981467,
          "alt": 1769
        },
        {
          "time": "2012-01-10T03:35:54Z",
          "lat": -33.231917,
          "fix": 583,
          "lng": 147.981733,
          "alt": 1762
        }
      ]
    }
  },
  {
    "inter": {
      "time": "2012-01-10T05:20:24.063627783402Z",
      "lat": -32.60363832,
      "fixFrac": 1835.0318138917016,
      "lng": 148.25639629,
      "alt": 1785.9
    },
    "cross": {
      "inZone": [
        false,
        true
      ],
      "crossingPair": [
        {
          "time": "2012-01-10T05:20:24Z",
          "lat": -32.60365,
          "fix": 1835,
          "lng": 148.2564,
          "alt": 1786
        },
        {
          "time": "2012-01-10T05:20:26Z",
          "lat": -32.603283,
          "fix": 1836,
          "lng": 148.256283,
          "alt": 1783
        }
      ]
    }
  },
  null
]
