[
  null,
  {
    "inter": {
      "time": "2012-01-10T03:37:00.08129199045Z",
      "lat": -33.23331317,
      "fixFrac": 558.2081291990453,
      "lng": 147.98281512
    },
    "cross": {
      "inZone": [
        true,
        false
      ],
      "crossingPair": [
        {
          "time": "2012-01-10T03:36:58Z",
          "lat": -33.233667,
          "fix": 558,
          "lng": 147.982867
        },
        {
          "time": "2012-01-10T03:37:08Z",
          "lat": -33.231967,
          "fix": 559,
          "lng": 147.982617
        }
      ]
    }
  },
  {
    "inter": {
      "time": "2012-01-10T05:32:02.046465156395Z",
      "lat": -32.602876,
      "fixFrac": 1247.0464651563955,
      "lng": 148.25724386
    },
    "cross": {
      "inZone": [
        false,
        true
      ],
      "crossingPair": [
        {
          "time": "2012-01-10T05:32:02Z",
          "lat": -32.602883,
          "fix": 1247,
          "lng": 148.25725
        },
        {
          "time": "2012-01-10T05:32:03Z",
          "lat": -32.602733,
          "fix": 1248,
          "lng": 148.257117
        }
      ]
    }
  },
  null
]
