{
  "zonesCrossNominees": [
    [
      {
        "inZone": [
          false,
          true
        ],
        "crossingPair": [
          {
            "time": "2012-01-13T02:37:42Z",
            "lat": -33.3628,
            "fix": 87,
            "lng": 147.93205,
            "alt": 1030
          },
          {
            "time": "2012-01-13T02:37:52Z",
            "lat": -33.362133,
            "fix": 88,
            "lng": 147.932533,
            "alt": 1060
          }
        ]
      },
      {
        "inZone": [
          true,
          false
        ],
        "crossingPair": [
          {
            "time": "2012-01-13T02:38:02Z",
            "lat": -33.36205,
            "fix": 89,
            "lng": 147.93275,
            "alt": 1086
          },
          {
            "time": "2012-01-13T02:38:12Z",
            "lat": -33.3622,
            "fix": 90,
            "lng": 147.933267,
            "alt": 1108
          }
        ]
      },
      {
        "inZone": [
          false,
          true
        ],
        "crossingPair": [
          {
            "time": "2012-01-13T02:40:52Z",
            "lat": -33.361683,
            "fix": 106,
            "lng": 147.933733,
            "alt": 1088
          },
          {
            "time": "2012-01-13T02:41:02Z",
            "lat": -33.36205,
            "fix": 107,
            "lng": 147.932683,
            "alt": 1084
          }
        ]
      },
      {
        "inZone": [
          true,
          false
        ],
        "crossingPair": [
          {
            "time": "2012-01-13T02:41:12Z",
            "lat": -33.361933,
            "fix": 108,
            "lng": 147.931533,
            "alt": 1072
          },
          {
            "time": "2012-01-13T02:41:22Z",
            "lat": -33.36185,
            "fix": 109,
            "lng": 147.9304,
            "alt": 1059
          }
        ]
      },
      {
        "inZone": [
          false,
          true
        ],
        "crossingPair": [
          {
            "time": "2012-01-13T02:42:03Z",
            "lat": -33.360567,
            "fix": 113,
            "lng": 147.93055,
            "alt": 1005
          },
          {
            "time": "2012-01-13T02:42:13Z",
            "lat": -33.361583,
            "fix": 114,
            "lng": 147.931483,
            "alt": 992
          }
        ]
      },
      {
        "inZone": [
          true,
          false
        ],
        "crossingPair": [
          {
            "time": "2012-01-13T02:42:43Z",
            "lat": -33.36085,
            "fix": 117,
            "lng": 147.932833,
            "alt": 973
          },
          {
            "time": "2012-01-13T02:42:53Z",
            "lat": -33.36,
            "fix": 118,
            "lng": 147.9319,
            "alt": 966
          }
        ]
      },
      {
        "inZone": [
          false,
          true
        ],
        "crossingPair": [
          {
            "time": "2012-01-13T02:43:03Z",
            "lat": -33.3605,
            "fix": 119,
            "lng": 147.93105,
            "alt": 976
          },
          {
            "time": "2012-01-13T02:43:13Z",
            "lat": -33.36075,
            "fix": 120,
            "lng": 147.932033,
            "alt": 980
          }
        ]
      },
      {
        "inZone": [
          true,
          false
        ],
        "crossingPair": [
          {
            "time": "2012-01-13T02:43:13Z",
            "lat": -33.36075,
            "fix": 120,
            "lng": 147.932033,
            "alt": 980
          },
          {
            "time": "2012-01-13T02:43:23Z",
            "lat": -33.359833,
            "fix": 121,
            "lng": 147.9317,
            "alt": 987
          }
        ]
      },
      {
        "inZone": [
          false,
          true
        ],
        "crossingPair": [
          {
            "time": "2012-01-13T02:43:53Z",
            "lat": -33.36045,
            "fix": 124,
            "lng": 147.932167,
            "alt": 1013
          },
          {
            "time": "2012-01-13T02:44:03Z",
            "lat": -33.360683,
            "fix": 125,
            "lng": 147.931533,
            "alt": 1034
          }
        ]
      },
      {
        "inZone": [
          true,
          false
        ],
        "crossingPair": [
          {
            "time": "2012-01-13T02:44:03Z",
            "lat": -33.360683,
            "fix": 125,
            "lng": 147.931533,
            "alt": 1034
          },
          {
            "time": "2012-01-13T02:44:13Z",
            "lat": -33.36035,
            "fix": 126,
            "lng": 147.932883,
            "alt": 1047
          }
        ]
      }
    ],
    [
      {
        "inZone": [
          true,
          false
        ],
        "crossingPair": [
          {
            "time": "2012-01-13T03:25:34Z",
            "lat": -33.279717,
            "fix": 374,
            "lng": 147.886083,
            "alt": 1738
          },
          {
            "time": "2012-01-13T03:25:44Z",
            "lat": -33.279033,
            "fix": 375,
            "lng": 147.884867,
            "alt": 1735
          }
        ]
      }
    ],
    [
      {
        "inZone": [
          false,
          true
        ],
        "crossingPair": [
          {
            "time": "2012-01-13T04:56:56Z",
            "lat": -32.9685,
            "fix": 921,
            "lng": 147.6064,
            "alt": 1680
          },
          {
            "time": "2012-01-13T04:57:03Z",
            "lat": -32.967817,
            "fix": 922,
            "lng": 147.605333,
            "alt": 1674
          }
        ]
      },
      {
        "inZone": [
          true,
          false
        ],
        "crossingPair": [
          {
            "time": "2012-01-13T04:57:14Z",
            "lat": -32.966817,
            "fix": 924,
            "lng": 147.605,
            "alt": 1667
          },
          {
            "time": "2012-01-13T04:57:24Z",
            "lat": -32.966883,
            "fix": 925,
            "lng": 147.607117,
            "alt": 1658
          }
        ]
      }
    ],
    [
      {
        "inZone": [
          false,
          true
        ],
        "crossingPair": [
          {
            "time": "2012-01-13T07:16:31Z",
            "lat": -32.760867,
            "fix": 1757,
            "lng": 148.64405,
            "alt": 1858
          },
          {
            "time": "2012-01-13T07:16:39Z",
            "lat": -32.761667,
            "fix": 1758,
            "lng": 148.6456,
            "alt": 1857
          }
        ]
      },
      {
        "inZone": [
          true,
          false
        ],
        "crossingPair": [
          {
            "time": "2012-01-13T07:17:00Z",
            "lat": -32.76375,
            "fix": 1761,
            "lng": 148.648783,
            "alt": 1845
          },
          {
            "time": "2012-01-13T07:17:10Z",
            "lat": -32.76515,
            "fix": 1762,
            "lng": 148.649767,
            "alt": 1846
          }
        ]
      }
    ],
    [
      {
        "inZone": [
          false,
          true
        ],
        "crossingPair": [
          {
            "time": "2012-01-13T08:02:23Z",
            "lat": -32.9357,
            "fix": 2033,
            "lng": 148.7494,
            "alt": 600
          },
          {
            "time": "2012-01-13T08:02:33Z",
            "lat": -32.936883,
            "fix": 2034,
            "lng": 148.750467,
            "alt": 597
          }
        ]
      }
    ]
  ],
  "zonesCrossExcluded": [],
  "startSelected": null,
  "zonesCrossSelected": [
    {
      "inZone": [
        false,
        true
      ],
      "crossingPair": [
        {
          "time": "2012-01-13T02:37:42Z",
          "lat": -33.3628,
          "fix": 87,
          "lng": 147.93205,
          "alt": 1030
        },
        {
          "time": "2012-01-13T02:37:52Z",
          "lat": -33.362133,
          "fix": 88,
          "lng": 147.932533,
          "alt": 1060
        }
      ]
    },
    {
      "inZone": [
        true,
        false
      ],
      "crossingPair": [
        {
          "time": "2012-01-13T03:25:34Z",
          "lat": -33.279717,
          "fix": 374,
          "lng": 147.886083,
          "alt": 1738
        },
        {
          "time": "2012-01-13T03:25:44Z",
          "lat": -33.279033,
          "fix": 375,
          "lng": 147.884867,
          "alt": 1735
        }
      ]
    },
    {
      "inZone": [
        false,
        true
      ],
      "crossingPair": [
        {
          "time": "2012-01-13T04:56:56Z",
          "lat": -32.9685,
          "fix": 921,
          "lng": 147.6064,
          "alt": 1680
        },
        {
          "time": "2012-01-13T04:57:03Z",
          "lat": -32.967817,
          "fix": 922,
          "lng": 147.605333,
          "alt": 1674
        }
      ]
    },
    {
      "inZone": [
        false,
        true
      ],
      "crossingPair": [
        {
          "time": "2012-01-13T07:16:31Z",
          "lat": -32.760867,
          "fix": 1757,
          "lng": 148.64405,
          "alt": 1858
        },
        {
          "time": "2012-01-13T07:16:39Z",
          "lat": -32.761667,
          "fix": 1758,
          "lng": 148.6456,
          "alt": 1857
        }
      ]
    },
    {
      "inZone": [
        false,
        true
      ],
      "crossingPair": [
        {
          "time": "2012-01-13T08:02:23Z",
          "lat": -32.9357,
          "fix": 2033,
          "lng": 148.7494,
          "alt": 600
        },
        {
          "time": "2012-01-13T08:02:33Z",
          "lat": -32.936883,
          "fix": 2034,
          "lng": 148.750467,
          "alt": 597
        }
      ]
    }
  ],
  "startNominees": []
}
