{
  "zonesCrossNominees": [
    [
      {
        "inZone": [
          true,
          false
        ],
        "crossingPair": [
          {
            "time": "2012-01-14T02:50:33Z",
            "lat": -33.3615,
            "fix": 28,
            "lng": 147.9315,
            "alt": 235
          },
          {
            "time": "2012-01-14T02:50:38Z",
            "lat": -33.361283,
            "fix": 29,
            "lng": 147.930633,
            "alt": 240
          }
        ]
      }
    ],
    [
      {
        "inZone": [
          true,
          false
        ],
        "crossingPair": [
          {
            "time": "2012-01-14T03:28:57Z",
            "lat": -33.4219,
            "fix": 488,
            "lng": 147.851933,
            "alt": 1678
          },
          {
            "time": "2012-01-14T03:29:02Z",
            "lat": -33.4223,
            "fix": 489,
            "lng": 147.851217,
            "alt": 1670
          }
        ]
      }
    ],
    [
      {
        "inZone": [
          false,
          true
        ],
        "crossingPair": [
          {
            "time": "2012-01-14T04:55:29Z",
            "lat": -33.708,
            "fix": 1525,
            "lng": 147.531417,
            "alt": 1273
          },
          {
            "time": "2012-01-14T04:55:34Z",
            "lat": -33.70845,
            "fix": 1526,
            "lng": 147.530583,
            "alt": 1260
          }
        ]
      },
      {
        "inZone": [
          true,
          false
        ],
        "crossingPair": [
          {
            "time": "2012-01-14T04:55:56Z",
            "lat": -33.70865,
            "fix": 1532,
            "lng": 147.527467,
            "alt": 1213
          },
          {
            "time": "2012-01-14T04:56:01Z",
            "lat": -33.70815,
            "fix": 1533,
            "lng": 147.527,
            "alt": 1212
          }
        ]
      },
      {
        "inZone": [
          false,
          true
        ],
        "crossingPair": [
          {
            "time": "2012-01-14T04:56:21Z",
            "lat": -33.708,
            "fix": 1537,
            "lng": 147.5248,
            "alt": 1222
          },
          {
            "time": "2012-01-14T04:56:26Z",
            "lat": -33.708517,
            "fix": 1538,
            "lng": 147.525483,
            "alt": 1221
          }
        ]
      },
      {
        "inZone": [
          true,
          false
        ],
        "crossingPair": [
          {
            "time": "2012-01-14T04:56:26Z",
            "lat": -33.708517,
            "fix": 1538,
            "lng": 147.525483,
            "alt": 1221
          },
          {
            "time": "2012-01-14T04:56:31Z",
            "lat": -33.708167,
            "fix": 1539,
            "lng": 147.526183,
            "alt": 1224
          }
        ]
      },
      {
        "inZone": [
          false,
          true
        ],
        "crossingPair": [
          {
            "time": "2012-01-14T04:56:36Z",
            "lat": -33.707933,
            "fix": 1540,
            "lng": 147.525733,
            "alt": 1226
          },
          {
            "time": "2012-01-14T04:56:41Z",
            "lat": -33.7086,
            "fix": 1541,
            "lng": 147.525567,
            "alt": 1228
          }
        ]
      },
      {
        "inZone": [
          true,
          false
        ],
        "crossingPair": [
          {
            "time": "2012-01-14T05:04:47Z",
            "lat": -33.710233,
            "fix": 1638,
            "lng": 147.542133,
            "alt": 1438
          },
          {
            "time": "2012-01-14T05:04:52Z",
            "lat": -33.70945,
            "fix": 1639,
            "lng": 147.5429,
            "alt": 1427
          }
        ]
      }
    ],
    [
      {
        "inZone": [
          false,
          true
        ],
        "crossingPair": [
          {
            "time": "2012-01-14T07:21:58Z",
            "lat": -33.133367,
            "fix": 3282,
            "lng": 147.572767,
            "alt": 1805
          },
          {
            "time": "2012-01-14T07:22:02Z",
            "lat": -33.132567,
            "fix": 3283,
            "lng": 147.572867,
            "alt": 1796
          }
        ]
      },
      {
        "inZone": [
          true,
          false
        ],
        "crossingPair": [
          {
            "time": "2012-01-14T07:22:33Z",
            "lat": -33.12905,
            "fix": 3290,
            "lng": 147.57715,
            "alt": 1745
          },
          {
            "time": "2012-01-14T07:22:38Z",
            "lat": -33.12865,
            "fix": 3291,
            "lng": 147.578117,
            "alt": 1737
          }
        ]
      }
    ],
    [
      {
        "inZone": [
          true,
          false
        ],
        "crossingPair": [
          {
            "time": "2012-01-14T02:50:33Z",
            "lat": -33.3615,
            "fix": 28,
            "lng": 147.9315,
            "alt": 235
          },
          {
            "time": "2012-01-14T02:50:38Z",
            "lat": -33.361283,
            "fix": 29,
            "lng": 147.930633,
            "alt": 240
          }
        ]
      }
    ]
  ],
  "zonesCrossExcluded": [],
  "startSelected": null,
  "zonesCrossSelected": [
    {
      "inZone": [
        true,
        false
      ],
      "crossingPair": [
        {
          "time": "2012-01-14T02:50:33Z",
          "lat": -33.3615,
          "fix": 28,
          "lng": 147.9315,
          "alt": 235
        },
        {
          "time": "2012-01-14T02:50:38Z",
          "lat": -33.361283,
          "fix": 29,
          "lng": 147.930633,
          "alt": 240
        }
      ]
    },
    {
      "inZone": [
        true,
        false
      ],
      "crossingPair": [
        {
          "time": "2012-01-14T03:28:57Z",
          "lat": -33.4219,
          "fix": 488,
          "lng": 147.851933,
          "alt": 1678
        },
        {
          "time": "2012-01-14T03:29:02Z",
          "lat": -33.4223,
          "fix": 489,
          "lng": 147.851217,
          "alt": 1670
        }
      ]
    },
    {
      "inZone": [
        false,
        true
      ],
      "crossingPair": [
        {
          "time": "2012-01-14T04:55:29Z",
          "lat": -33.708,
          "fix": 1525,
          "lng": 147.531417,
          "alt": 1273
        },
        {
          "time": "2012-01-14T04:55:34Z",
          "lat": -33.70845,
          "fix": 1526,
          "lng": 147.530583,
          "alt": 1260
        }
      ]
    },
    {
      "inZone": [
        false,
        true
      ],
      "crossingPair": [
        {
          "time": "2012-01-14T07:21:58Z",
          "lat": -33.133367,
          "fix": 3282,
          "lng": 147.572767,
          "alt": 1805
        },
        {
          "time": "2012-01-14T07:22:02Z",
          "lat": -33.132567,
          "fix": 3283,
          "lng": 147.572867,
          "alt": 1796
        }
      ]
    },
    null
  ],
  "startNominees": []
}
