[
  {
    "inter": {
      "time": "2012-01-05T02:52:47.950132756136Z",
      "lat": -33.36188165,
      "fixFrac": 82.7437665945177,
      "lng": 147.93117795,
      "alt": 241.67
    },
    "cross": {
      "inZone": [
        true,
        false
      ],
      "crossingPair": [
        {
          "time": "2012-01-05T02:52:42Z",
          "lat": -33.361541,
          "fix": 82,
          "lng": 147.932037,
          "alt": 232
        },
        {
          "time": "2012-01-05T02:52:50Z",
          "lat": -33.361999,
          "fix": 83,
          "lng": 147.930882,
          "alt": 245
        }
      ]
    }
  },
  {
    "inter": {
      "time": "2012-01-05T03:44:56.54805317936Z",
      "lat": -33.45172613,
      "fixFrac": 473.8185066474207,
      "lng": 147.92948871,
      "alt": 1449.27
    },
    "cross": {
      "inZone": [
        true,
        false
      ],
      "crossingPair": [
        {
          "time": "2012-01-05T03:44:50Z",
          "lat": -33.451127,
          "fix": 473,
          "lng": 147.929907,
          "alt": 1446
        },
        {
          "time": "2012-01-05T03:44:58Z",
          "lat": -33.451859,
          "fix": 474,
          "lng": 147.929396,
          "alt": 1450
        }
      ]
    }
  },
  null,
  null,
  null
]
