[
  {
    "inter": {
      "time": "2012-01-07T02:41:36.98657936397Z",
      "lat": -33.36187984,
      "fixFrac": 0.19731587279493004,
      "lng": 147.931183
    },
    "cross": {
      "inZone": [
        false,
        true
      ],
      "crossingPair": [
        {
          "time": "2012-01-07T02:41:36Z",
          "lat": -33.361883,
          "fix": 0,
          "lng": 147.931183
        },
        {
          "time": "2012-01-07T02:41:41Z",
          "lat": -33.361867,
          "fix": 1,
          "lng": 147.931183
        }
      ]
    }
  },
  {
    "inter": {
      "time": "2012-01-07T03:40:06.18185889706Z",
      "lat": -33.58240329,
      "fixFrac": 701.6363717794127,
      "lng": 147.98139653
    },
    "cross": {
      "inZone": [
        true,
        false
      ],
      "crossingPair": [
        {
          "time": "2012-01-07T03:40:03Z",
          "lat": -33.582117,
          "fix": 701,
          "lng": 147.981683
        },
        {
          "time": "2012-01-07T03:40:08Z",
          "lat": -33.582567,
          "fix": 702,
          "lng": 147.981233
        }
      ]
    }
  },
  {
    "inter": {
      "time": "2012-01-07T04:47:11.427493653095Z",
      "lat": -34.01766472,
      "fixFrac": 1504.8854987306195,
      "lng": 148.22190101
    },
    "cross": {
      "inZone": [
        false,
        true
      ],
      "crossingPair": [
        {
          "time": "2012-01-07T04:47:07Z",
          "lat": -34.01675,
          "fix": 1504,
          "lng": 148.221267
        },
        {
          "time": "2012-01-07T04:47:12Z",
          "lat": -34.017783,
          "fix": 1505,
          "lng": 148.221983
        }
      ]
    }
  },
  {
    "inter": {
      "time": "2012-01-07T05:12:05.072681997096Z",
      "lat": -34.11780402,
      "fixFrac": 1804.768170499275,
      "lng": 148.49695843
    },
    "cross": {
      "inZone": [
        false,
        true
      ],
      "crossingPair": [
        {
          "time": "2012-01-07T05:12:02Z",
          "lat": -34.117983,
          "fix": 1804,
          "lng": 148.496433
        },
        {
          "time": "2012-01-07T05:12:06Z",
          "lat": -34.11775,
          "fix": 1805,
          "lng": 148.497117
        }
      ]
    }
  },
  {
    "inter": {
      "time": "2012-01-07T06:33:51.927556779451Z",
      "lat": -34.8129795,
      "fixFrac": 2785.927556779452,
      "lng": 148.66516092
    },
    "cross": {
      "inZone": [
        false,
        true
      ],
      "crossingPair": [
        {
          "time": "2012-01-07T06:33:51Z",
          "lat": -34.812717,
          "fix": 2785,
          "lng": 148.665083
        },
        {
          "time": "2012-01-07T06:33:52Z",
          "lat": -34.813,
          "fix": 2786,
          "lng": 148.665167
        }
      ]
    }
  }
]
