[
  {
    "inter": {
      "time": "2012-01-06T02:57:14.118674398584Z",
      "lat": -33.36103893,
      "fixFrac": 128.7062247995286,
      "lng": 147.93307113
    },
    "cross": {
      "inZone": [
        false,
        true
      ],
      "crossingPair": [
        {
          "time": "2012-01-06T02:57:12Z",
          "lat": -33.360933,
          "fix": 128,
          "lng": 147.933283
        },
        {
          "time": "2012-01-06T02:57:15Z",
          "lat": -33.361083,
          "fix": 129,
          "lng": 147.932983
        }
      ]
    }
  },
  {
    "inter": {
      "time": "2012-01-06T04:00:17.630813927114Z",
      "lat": -33.31682786,
      "fixFrac": 1382.2102713090383,
      "lng": 147.93944352
    },
    "cross": {
      "inZone": [
        true,
        false
      ],
      "crossingPair": [
        {
          "time": "2012-01-06T04:00:17Z",
          "lat": -33.316933,
          "fix": 1382,
          "lng": 147.939433
        },
        {
          "time": "2012-01-06T04:00:20Z",
          "lat": -33.316433,
          "fix": 1383,
          "lng": 147.939483
        }
      ]
    }
  },
  {
    "inter": {
      "time": "2012-01-06T05:24:09.341936766739Z",
      "lat": -32.90558392,
      "fixFrac": 3046.780645588914,
      "lng": 147.98337082
    },
    "cross": {
      "inZone": [
        false,
        true
      ],
      "crossingPair": [
        {
          "time": "2012-01-06T05:24:07Z",
          "lat": -32.906,
          "fix": 3046,
          "lng": 147.983267
        },
        {
          "time": "2012-01-06T05:24:10Z",
          "lat": -32.905467,
          "fix": 3047,
          "lng": 147.9834
        }
      ]
    }
  },
  {
    "inter": {
      "time": "2012-01-06T06:46:16.147873127986Z",
      "lat": -32.95243415,
      "fixFrac": 4679.147873127987,
      "lng": 147.5586256
    },
    "cross": {
      "inZone": [
        false,
        true
      ],
      "crossingPair": [
        {
          "time": "2012-01-06T06:46:16Z",
          "lat": -32.952417,
          "fix": 4679,
          "lng": 147.558633
        },
        {
          "time": "2012-01-06T06:46:17Z",
          "lat": -32.952533,
          "fix": 4680,
          "lng": 147.558583
        }
      ]
    }
  },
  {
    "inter": {
      "time": "2012-01-06T08:25:23.939700163054Z",
      "lat": -33.12410666,
      "fixFrac": 6647.646566721019,
      "lng": 147.90672029
    },
    "cross": {
      "inZone": [
        false,
        true
      ],
      "crossingPair": [
        {
          "time": "2012-01-06T08:25:22Z",
          "lat": -33.123967,
          "fix": 6647,
          "lng": 147.906483
        },
        {
          "time": "2012-01-06T08:25:25Z",
          "lat": -33.124183,
          "fix": 6648,
          "lng": 147.90685
        }
      ]
    }
  }
]
