[
  {
    "inter": {
      "time": "2012-01-14T02:47:33.112361832236Z",
      "lat": -33.36071922,
      "fixFrac": 26.370787277412457,
      "lng": 147.93132684
    },
    "cross": {
      "inZone": [
        true,
        false
      ],
      "crossingPair": [
        {
          "time": "2012-01-14T02:47:32Z",
          "lat": -33.36075,
          "fix": 26,
          "lng": 147.9315
        },
        {
          "time": "2012-01-14T02:47:35Z",
          "lat": -33.360667,
          "fix": 27,
          "lng": 147.931033
        }
      ]
    }
  },
  {
    "inter": {
      "time": "2012-01-14T03:36:14.369534550063Z",
      "lat": -33.40388343,
      "fixFrac": 991.789844850022,
      "lng": 147.8371627
    },
    "cross": {
      "inZone": [
        true,
        false
      ],
      "crossingPair": [
        {
          "time": "2012-01-14T03:36:12Z",
          "lat": -33.403633,
          "fix": 991,
          "lng": 147.83765
        },
        {
          "time": "2012-01-14T03:36:15Z",
          "lat": -33.40395,
          "fix": 992,
          "lng": 147.837033
        }
      ]
    }
  },
  {
    "inter": {
      "time": "2012-01-14T04:36:10.936275634241Z",
      "lat": -33.70879574,
      "fixFrac": 2178.936275634241,
      "lng": 147.53520638
    },
    "cross": {
      "inZone": [
        false,
        true
      ],
      "crossingPair": [
        {
          "time": "2012-01-14T04:36:10Z",
          "lat": -33.708733,
          "fix": 2178,
          "lng": 147.5353
        },
        {
          "time": "2012-01-14T04:36:11Z",
          "lat": -33.7088,
          "fix": 2179,
          "lng": 147.5352
        }
      ]
    }
  },
  {
    "inter": {
      "time": "2012-01-14T06:59:16.348792940528Z",
      "lat": -33.13266994,
      "fixFrac": 5011.674396470265,
      "lng": 147.57295554
    },
    "cross": {
      "inZone": [
        false,
        true
      ],
      "crossingPair": [
        {
          "time": "2012-01-14T06:59:15Z",
          "lat": -33.13285,
          "fix": 5011,
          "lng": 147.572967
        },
        {
          "time": "2012-01-14T06:59:17Z",
          "lat": -33.132583,
          "fix": 5012,
          "lng": 147.57295
        }
      ]
    }
  },
  null
]
