[
  [
    [
      "100",
      "Attila Bertok"
    ],
    {
      "area": "89396500.5561 km^2 s",
      "frac": 1,
      "coef": 3.13061964
    }
  ],
  [
    [
      "106",
      "Adam Parer"
    ],
    {
      "area": "90837366.7117 km^2 s",
      "frac": 0.90665762,
      "coef": 3.18107803
    }
  ],
  [
    [
      "15",
      "Jean Souviron "
    ],
    {
      "area": "91631953.9522 km^2 s",
      "frac": 0.87490494,
      "coef": 3.20890407
    }
  ],
  [
    [
      "21",
      "Gavin Myers"
    ],
    {
      "area": "92227949.0724 km^2 s",
      "frac": 0.85355692,
      "coef": 3.22977552
    }
  ],
  [
    [
      "13",
      "John Smith"
    ],
    {
      "area": "100553527.2372 km^2 s",
      "frac": 0.63466153,
      "coef": 3.521333
    }
  ],
  [
    [
      "1",
      "Lukas Bader"
    ],
    {
      "area": "100753538.7134 km^2 s",
      "frac": 0.6303082,
      "coef": 3.5283373
    }
  ],
  [
    [
      "60",
      "Rohan Holtkamp"
    ],
    {
      "area": "100881488.0729 km^2 s",
      "frac": 0.62753674,
      "coef": 3.53281802
    }
  ],
  [
    [
      "61",
      "Jonny Durand"
    ],
    {
      "area": "101289279.6529 km^2 s",
      "frac": 0.61877153,
      "coef": 3.54709867
    }
  ],
  [
    [
      "66",
      "Jonas Lobitz"
    ],
    {
      "area": "101598386.6114 km^2 s",
      "frac": 0.61219411,
      "coef": 3.55792344
    }
  ],
  [
    [
      "95",
      "Anton Struganov"
    ],
    {
      "area": "101603282.3327 km^2 s",
      "frac": 0.61209039,
      "coef": 3.55809488
    }
  ],
  [
    [
      "23",
      "Gerolf Heinrichs"
    ],
    {
      "area": "101641241.1583 km^2 s",
      "frac": 0.61128663,
      "coef": 3.55942418
    }
  ],
  [
    [
      "56",
      "Cameron Tunbridge"
    ],
    {
      "area": "101670903.1392 km^2 s",
      "frac": 0.61065913,
      "coef": 3.56046293
    }
  ],
  [
    [
      "90",
      "Adam Stevens"
    ],
    {
      "area": "101967098.7471 km^2 s",
      "frac": 0.60442055,
      "coef": 3.57083555
    }
  ],
  [
    [
      "96",
      "Brodrick Osborne"
    ],
    {
      "area": "102451086.7670 km^2 s",
      "frac": 0.59433099,
      "coef": 3.58778456
    }
  ],
  [
    [
      "42",
      "Suan Selenati"
    ],
    {
      "area": "103313745.7976 km^2 s",
      "frac": 0.57665093,
      "coef": 3.61799444
    }
  ],
  [
    [
      "68",
      "Grant Heaney"
    ],
    {
      "area": "103368505.0291 km^2 s",
      "frac": 0.57554118,
      "coef": 3.61991208
    }
  ],
  [
    [
      "89",
      "Scott Barrett"
    ],
    {
      "area": "104187511.0445 km^2 s",
      "frac": 0.55911196,
      "coef": 3.64859325
    }
  ],
  [
    [
      "59",
      "Artur Dzamikhov"
    ],
    {
      "area": "105400116.7069 km^2 s",
      "frac": 0.53533299,
      "coef": 3.69105808
    }
  ],
  [
    [
      "7",
      "Shaun O'neill"
    ],
    {
      "area": "105739262.3791 km^2 s",
      "frac": 0.5287912,
      "coef": 3.70293478
    }
  ],
  [
    [
      "94",
      "Mitch Shipley"
    ],
    {
      "area": "105803558.4752 km^2 s",
      "frac": 0.52755612,
      "coef": 3.7051864
    }
  ],
  [
    [
      "34",
      "Jon snr Durand"
    ],
    {
      "area": "106062680.2907 km^2 s",
      "frac": 0.52259482,
      "coef": 3.71426071
    }
  ],
  [
    [
      "45",
      "Roland Wöhrle"
    ],
    {
      "area": "106092301.4598 km^2 s",
      "frac": 0.52202932,
      "coef": 3.71529803
    }
  ],
  [
    [
      "92",
      "Hans Kiefinger"
    ],
    {
      "area": "106217338.1523 km^2 s",
      "frac": 0.5196459,
      "coef": 3.71967675
    }
  ],
  [
    [
      "31",
      "Andrew Barnes"
    ],
    {
      "area": "106899953.0262 km^2 s",
      "frac": 0.50673659,
      "coef": 3.74358158
    }
  ],
  [
    [
      "26",
      "Guy Hubbard"
    ],
    {
      "area": "106948276.0142 km^2 s",
      "frac": 0.50582915,
      "coef": 3.74527382
    }
  ],
  [
    [
      "25",
      "Nick Purcell"
    ],
    {
      "area": "107261517.4818 km^2 s",
      "frac": 0.49996695,
      "coef": 3.75624338
    }
  ],
  [
    [
      "93",
      "Trent Brown"
    ],
    {
      "area": "107285986.4372 km^2 s",
      "frac": 0.49951047,
      "coef": 3.75710027
    }
  ],
  [
    [
      "18",
      "Jürgen Pasker"
    ],
    {
      "area": "107786739.0044 km^2 s",
      "frac": 0.49021389,
      "coef": 3.77463637
    }
  ],
  [
    [
      "44",
      "Francoise Dieuzeide-banet"
    ],
    {
      "area": "108049509.7909 km^2 s",
      "frac": 0.4853693,
      "coef": 3.78383846
    }
  ],
  [
    [
      "99",
      "Tullio Gervasoni"
    ],
    {
      "area": "108277613.5888 km^2 s",
      "frac": 0.48118226,
      "coef": 3.79182654
    }
  ],
  [
    [
      "5",
      "Wolfgang Siess"
    ],
    {
      "area": "108696053.1446 km^2 s",
      "frac": 0.47354501,
      "coef": 3.80648008
    }
  ],
  [
    [
      "55",
      "Kari Suhonen"
    ],
    {
      "area": "108726117.1798 km^2 s",
      "frac": 0.47299842,
      "coef": 3.80753291
    }
  ],
  [
    [
      "6",
      "Phil Schroder"
    ],
    {
      "area": "108787786.1826 km^2 s",
      "frac": 0.47187812,
      "coef": 3.80969252
    }
  ],
  [
    [
      "62",
      "Enda Murphy"
    ],
    {
      "area": "108980134.1199 km^2 s",
      "frac": 0.46839147,
      "coef": 3.81642845
    }
  ],
  [
    [
      "33",
      "Conrad Loten"
    ],
    {
      "area": "109097847.1752 km^2 s",
      "frac": 0.46626334,
      "coef": 3.8205507
    }
  ],
  [
    [
      "24",
      "Christian Baertschi"
    ],
    {
      "area": "109146380.0478 km^2 s",
      "frac": 0.46538715,
      "coef": 3.8222503
    }
  ],
  [
    [
      "78",
      "Christine Aichner"
    ],
    {
      "area": "109903699.0445 km^2 s",
      "frac": 0.45180638,
      "coef": 3.84877122
    }
  ],
  [
    [
      "71",
      "Edoardo Giudiceandrea"
    ],
    {
      "area": "112016206.8027 km^2 s",
      "frac": 0.41477744,
      "coef": 3.92275016
    }
  ],
  [
    [
      "46",
      "Jonathon Foote"
    ],
    {
      "area": "112354559.9446 km^2 s",
      "frac": 0.40895592,
      "coef": 3.93459911
    }
  ],
  [
    [
      "75",
      "Joerg Bajewski"
    ],
    {
      "area": "112764887.5100 km^2 s",
      "frac": 0.40193428,
      "coef": 3.94896858
    }
  ],
  [
    [
      "84",
      "Yasuhiro Noma"
    ],
    {
      "area": "113101220.7143 km^2 s",
      "frac": 0.39620945,
      "coef": 3.96074679
    }
  ],
  [
    [
      "14",
      "Olav Lien Olsen"
    ],
    {
      "area": "113920128.5448 km^2 s",
      "frac": 0.38238253,
      "coef": 3.98942452
    }
  ],
  [
    [
      "19",
      "Mikhail Karmazin"
    ],
    {
      "area": "114928770.1025 km^2 s",
      "frac": 0.36556173,
      "coef": 4.02474663
    }
  ],
  [
    [
      "11",
      "Steve Blenkinsop"
    ],
    {
      "area": "115460059.8908 km^2 s",
      "frac": 0.35679081,
      "coef": 4.04335213
    }
  ],
  [
    [
      "12",
      "Glen Mcfarlane"
    ],
    {
      "area": "116458114.9702 km^2 s",
      "frac": 0.34047354,
      "coef": 4.07830351
    }
  ],
  [
    [
      "32",
      "Kathryn O'Riordan"
    ],
    {
      "area": "117163439.1052 km^2 s",
      "frac": 0.32906298,
      "coef": 4.1030036
    }
  ],
  [
    [
      "29",
      "Konstantin Lukyanov"
    ],
    {
      "area": "118642744.4898 km^2 s",
      "frac": 0.30543992,
      "coef": 4.15480811
    }
  ],
  [
    [
      "87",
      "Corinna Schwiegershausen"
    ],
    {
      "area": "119736219.5520 km^2 s",
      "frac": 0.28823364,
      "coef": 4.19310105
    }
  ],
  [
    [
      "77",
      "Len Paton"
    ],
    {
      "area": "119992799.9554 km^2 s",
      "frac": 0.28422638,
      "coef": 4.20208637
    }
  ],
  [
    [
      "36",
      "Franz Herrmann"
    ],
    {
      "area": "123871135.6645 km^2 s",
      "frac": 0.22495032,
      "coef": 4.33790369
    }
  ],
  [
    [
      "3",
      "Rod Flockhart"
    ],
    {
      "area": "123902104.0729 km^2 s",
      "frac": 0.22448624,
      "coef": 4.33898819
    }
  ],
  [
    [
      "51",
      "Rob In 't Groen"
    ],
    {
      "area": "125881951.3976 km^2 s",
      "frac": 0.1950982,
      "coef": 4.40832143
    }
  ],
  [
    [
      "98",
      "Patrick Collin"
    ],
    {
      "area": "129629743.8930 km^2 s",
      "frac": 0.14088141,
      "coef": 4.5395672
    }
  ],
  [
    [
      "47",
      "Miguel De Jong "
    ],
    {
      "area": "131242974.8198 km^2 s",
      "frac": 0.11806684,
      "coef": 4.59606172
    }
  ],
  [
    [
      "69",
      "Jonathan Kinred"
    ],
    {
      "area": "134381296.1654 km^2 s",
      "frac": 0.07450604,
      "coef": 4.70596413
    }
  ],
  [
    [
      "8",
      "Primoz Gricar"
    ],
    {
      "area": "135421418.0323 km^2 s",
      "frac": 0.0602945,
      "coef": 4.74238866
    }
  ],
  [
    [
      "82",
      "Alain Le-gac"
    ],
    {
      "area": "137908253.7263 km^2 s",
      "frac": 0.02674255,
      "coef": 4.82947638
    }
  ],
  [
    [
      "43",
      "Les Bestt"
    ],
    {
      "area": "139114154.0662 km^2 s",
      "frac": 0.01067989,
      "coef": 4.87170639
    }
  ],
  [
    [
      "70",
      "Matthew Barlow"
    ],
    {
      "area": "139649559.4090 km^2 s",
      "frac": 0.00358997,
      "coef": 4.89045601
    }
  ],
  [
    [
      "85",
      "Neil Petersen"
    ],
    {
      "area": "140294869.8815 km^2 s",
      "frac": 0,
      "coef": 4.91305445
    }
  ],
  [
    [
      "101",
      "Andrew Luton "
    ],
    {
      "area": "141050189.0345 km^2 s",
      "frac": 0,
      "coef": 4.93950534
    }
  ],
  [
    [
      "16",
      "Grant Edward"
    ],
    {
      "area": "143276929.9874 km^2 s",
      "frac": 0,
      "coef": 5.01748467
    }
  ],
  [
    [
      "41",
      "Curt Warren"
    ],
    {
      "area": "151359745.0766 km^2 s",
      "frac": 0,
      "coef": 5.30054071
    }
  ],
  [
    [
      "17",
      "John Urlich"
    ],
    {
      "area": "153633337.6636 km^2 s",
      "frac": 0,
      "coef": 5.38016076
    }
  ],
  [
    [
      "79",
      "David Stevens"
    ],
    {
      "area": "155434742.2329 km^2 s",
      "frac": 0,
      "coef": 5.44324502
    }
  ],
  [
    [
      "49",
      "Tony Giammichele"
    ],
    {
      "area": "156289874.2097 km^2 s",
      "frac": 0,
      "coef": 5.47319131
    }
  ],
  [
    [
      "105",
      "Chris Lawry"
    ],
    {
      "area": "156379840.6522 km^2 s",
      "frac": 0,
      "coef": 5.47634188
    }
  ],
  [
    [
      "73",
      "Gijs Wanders"
    ],
    {
      "area": "161351007.9301 km^2 s",
      "frac": 0,
      "coef": 5.65042961
    }
  ],
  [
    [
      "102",
      "Davide Guiducci"
    ],
    {
      "area": "163642052.9039 km^2 s",
      "frac": 0,
      "coef": 5.73066084
    }
  ],
  [
    [
      "52",
      "Virpi Nieminen"
    ],
    {
      "area": "165751438.1738 km^2 s",
      "frac": 0,
      "coef": 5.80453043
    }
  ],
  [
    [
      "83",
      "Peter Dall"
    ],
    {
      "area": "170295362.4058 km^2 s",
      "frac": 0,
      "coef": 5.96365633
    }
  ],
  [
    [
      "20",
      "Luke Browne "
    ],
    {
      "area": "176270781.2084 km^2 s",
      "frac": 0,
      "coef": 6.17291243
    }
  ],
  [
    [
      "22",
      "Mark Russell"
    ],
    {
      "area": "178377361.0960 km^2 s",
      "frac": 0,
      "coef": 6.24668378
    }
  ],
  [
    [
      "76",
      "Dmitriy Korchenkov"
    ],
    {
      "area": "206745527.9064 km^2 s",
      "frac": 0,
      "coef": 7.24012244
    }
  ],
  [
    [
      "97",
      "Konrad Schwab"
    ],
    {
      "area": "209514172.6360 km^2 s",
      "frac": 0,
      "coef": 7.33707896
    }
  ],
  [
    [
      "53",
      "Hadewych van Kempen"
    ],
    {
      "area": "209930850.8052 km^2 s",
      "frac": 0,
      "coef": 7.35167082
    }
  ],
  [
    [
      "2",
      "Pablo Gomes"
    ],
    {
      "area": "213828801.2998 km^2 s",
      "frac": 0,
      "coef": 7.48817505
    }
  ],
  [
    [
      "40",
      "Phil de Joux"
    ],
    {
      "area": "214463192.9773 km^2 s",
      "frac": 0,
      "coef": 7.51039112
    }
  ],
  [
    [
      "64",
      "Gustavo Carvalho"
    ],
    {
      "area": "221595896.7452 km^2 s",
      "frac": 0,
      "coef": 7.76017475
    }
  ],
  [
    [
      "27",
      "Boris Marold "
    ],
    {
      "area": "222706776.6936 km^2 s",
      "frac": 0,
      "coef": 7.7990772
    }
  ],
  [
    [
      "37",
      "Peter Ebeling"
    ],
    {
      "area": "232642433.4466 km^2 s",
      "frac": 0,
      "coef": 8.1470188
    }
  ]
]
